[{"id":3086212,"name":"Ściegny, Poland (15.78&#176;, 50.79&#176;)"},{"id":7533214,"name":"Ścinawa, Poland (16.43&#176;, 51.41&#176;)"},{"id":3086206,"name":"Ścinawa, Poland (16.43&#176;, 51.42&#176;)"},{"id":3085584,"name":"Ślemień, Poland (19.37&#176;, 49.72&#176;)"},{"id":3085577,"name":"Ślesin, Poland (17.70&#176;, 53.17&#176;)"},{"id":3085578,"name":"Ślesin, Poland (18.31&#176;, 52.37&#176;)"},{"id":3085565,"name":"Śliwice, Poland (18.17&#176;, 53.71&#176;)"},{"id":3085391,"name":"Śmigiel, Poland (16.53&#176;, 52.01&#176;)"},{"id":3085384,"name":"Śmiłowo, Poland (16.92&#176;, 53.14&#176;)"},{"id":758746,"name":"Śniadowo, Poland (21.99&#176;, 53.04&#176;)"},{"id":3085056,"name":"Śrem, Poland (17.02&#176;, 52.09&#176;)"},{"id":7533378,"name":"Śrem, Poland (17.02&#176;, 52.09&#176;)"},{"id":3085045,"name":"Środa Wielkopolska, Poland (17.28&#176;, 52.23&#176;)"},{"id":7533339,"name":"Środa Wielkopolska, Poland (17.28&#176;, 52.23&#176;)"},{"id":3085047,"name":"Środa Śląska, Poland (16.60&#176;, 51.16&#176;)"},{"id":3085041,"name":"Śródmieście, Poland (19.94&#176;, 50.06&#176;)"},{"id":3084092,"name":"Świdnica, Poland (15.39&#176;, 51.89&#176;)"},{"id":3084093,"name":"Świdnica, Poland (16.49&#176;, 50.84&#176;)"},{"id":7532248,"name":"Świdnica, Poland (16.49&#176;, 50.84&#176;)"},{"id":757690,"name":"Świdnik Mały, Poland (22.68&#176;, 51.26&#176;)"},{"id":7531487,"name":"Świdnik, Poland (22.68&#176;, 51.22&#176;)"},{"id":757692,"name":"Świdnik, Poland (22.70&#176;, 51.22&#176;)"},{"id":3084085,"name":"Świdwin, Poland (15.78&#176;, 53.77&#176;)"},{"id":7531696,"name":"Świdwin, Poland (15.80&#176;, 53.77&#176;)"},{"id":3084084,"name":"Świebodzice, Poland (16.33&#176;, 50.86&#176;)"},{"id":7531967,"name":"Świebodzice, Poland (16.34&#176;, 50.87&#176;)"},{"id":7533428,"name":"Świebodzin, Poland (15.53&#176;, 52.24&#176;)"},{"id":3084062,"name":"Świebodzin, Poland (15.53&#176;, 52.25&#176;)"},{"id":3084069,"name":"Świecie nad Osą, Poland (19.10&#176;, 53.44&#176;)"},{"id":7533276,"name":"Świecie, Poland (18.42&#176;, 53.40&#176;)"},{"id":3084074,"name":"Świecie, Poland (18.45&#176;, 53.41&#176;)"},{"id":3084061,"name":"Świedziebnia, Poland (19.55&#176;, 53.15&#176;)"},{"id":3084060,"name":"Świekatowo, Poland (18.10&#176;, 53.42&#176;)"},{"id":7531973,"name":"Świeradów-Zdrój, Poland (15.32&#176;, 50.92&#176;)"},{"id":3084055,"name":"Świeradów-Zdrój, Poland (15.34&#176;, 50.91&#176;)"},{"id":7535607,"name":"Świercze, Poland (20.76&#176;, 52.67&#176;)"},{"id":3084052,"name":"Świerczewo, Poland (16.88&#176;, 52.37&#176;)"},{"id":3084051,"name":"Świerczów, Poland (17.76&#176;, 50.96&#176;)"},{"id":3084033,"name":"Świerklaniec, Poland (18.94&#176;, 50.44&#176;)"},{"id":7531935,"name":"Świerklaniec, Poland (18.94&#176;, 50.44&#176;)"},{"id":3084030,"name":"Świerklany Dolne, Poland (18.58&#176;, 50.02&#176;)"},{"id":3084029,"name":"Świerklany Górne, Poland (18.59&#176;, 50.03&#176;)"},{"id":7532592,"name":"Świerklany, Poland (18.58&#176;, 50.02&#176;)"},{"id":3084024,"name":"Świerzawa, Poland (15.90&#176;, 51.01&#176;)"},{"id":3084020,"name":"Świerzno, Poland (14.97&#176;, 53.96&#176;)"},{"id":757585,"name":"Świlcza, Poland (21.90&#176;, 50.07&#176;)"},{"id":3083964,"name":"Świnice Warckie, Poland (18.92&#176;, 52.04&#176;)"},{"id":3083958,"name":"Świnna, Poland (19.25&#176;, 49.66&#176;)"},{"id":3083956,"name":"Świnobród, Poland (17.06&#176;, 50.85&#176;)"},{"id":3083955,"name":"Świnoujście, Poland (14.25&#176;, 53.91&#176;)"},{"id":7530749,"name":"Świnoujście, Poland (14.31&#176;, 53.85&#176;)"},{"id":7532101,"name":"Świnoujście, Poland (14.31&#176;, 53.85&#176;)"},{"id":3084107,"name":"Świątniki Górne, Poland (19.95&#176;, 49.93&#176;)"},{"id":7533033,"name":"Świątniki Górne, Poland (19.95&#176;, 49.93&#176;)"},{"id":3084071,"name":"Święciechowa, Poland (16.50&#176;, 51.86&#176;)"},{"id":3084005,"name":"Święta Katarzyna, Poland (17.11&#176;, 51.03&#176;)"},{"id":757610,"name":"Świętajno, Poland (21.22&#176;, 53.57&#176;)"},{"id":7530992,"name":"Świętochłowice, Poland (18.91&#176;, 50.30&#176;)"},{"id":7532438,"name":"Świętochłowice, Poland (18.91&#176;, 50.30&#176;)"},{"id":3083988,"name":"Świętochłowice, Poland (18.92&#176;, 50.30&#176;)"}]